opsep/__init__.py
opsep/main.py
opsep/opsep.py
opsep/pyca.py
opsep/utils.py
tests/__init__.py
tests/test_client.py
tests/test_pyca.py
tests/utils.py
opsep-3.1.2.dist-info/LICENSE
opsep-3.1.2.dist-info/METADATA
opsep-3.1.2.dist-info/WHEEL
opsep-3.1.2.dist-info/top_level.txt
opsep-3.1.2.dist-info/RECORD
