Metadata-Version: 2.1
Name: opsep
Version: 3.1.2
Summary: OpSep Python Library
Home-page: https://github.com/opsep/opsep-python/
Author: Michael Flaxman
Author-email: opsep-python@michaelflaxman.com
License: UNKNOWN
Platform: UNKNOWN
Classifier: Programming Language :: Python :: 3
Classifier: License :: OSI Approved :: MIT License
Classifier: Operating System :: OS Independent
Requires-Python: >=3.3
Requires-Dist: cryptography (==2.9.2)
Requires-Dist: pytest
Requires-Dist: requests
